cli/__init__.py
cli/main.py
cli/utils/__init__.py
cli/utils/gh_utils.py
derek_git-0.0.3.dist-info/LICENSE
derek_git-0.0.3.dist-info/METADATA
derek_git-0.0.3.dist-info/WHEEL
derek_git-0.0.3.dist-info/entry_points.txt
derek_git-0.0.3.dist-info/top_level.txt
derek_git-0.0.3.dist-info/RECORD
