Metadata-Version: 2.1
Name: derek-git
Version: 0.0.3
License-File: LICENSE
Requires-Dist: Click
Requires-Dist: GitPython
